stytch_management/__init__.py
stytch_management/attribute.py
stytch_management/client.py
stytch_management/country_code_allowlist.py
stytch_management/emailtemplates.py
stytch_management/environments.py
stytch_management/errors.py
stytch_management/event_log_streaming.py
stytch_management/http_client.py
stytch_management/jwttemplates.py
stytch_management/passwordstrengthconfig.py
stytch_management/project.py
stytch_management/projects.py
stytch_management/publictokens.py
stytch_management/py.typed
stytch_management/rbacpolicy.py
stytch_management/redirecturls.py
stytch_management/sdk.py
stytch_management/secrets.py
stytch_management/trustedtokenprofiles.py
stytch_management/version.py
stytch_management/models/__init__.py
stytch_management/models/attribute.py
stytch_management/models/country_code_allowlist.py
stytch_management/models/emailtemplates.py
stytch_management/models/environments.py
stytch_management/models/event_log_streaming.py
stytch_management/models/jwttemplates.py
stytch_management/models/passwordstrengthconfig.py
stytch_management/models/project.py
stytch_management/models/projects.py
stytch_management/models/publictokens.py
stytch_management/models/rbacpolicy.py
stytch_management/models/redirecturls.py
stytch_management/models/sdk.py
stytch_management/models/secrets.py
stytch_management/models/trustedtokenprofiles.py
stytch_management-1.1.0.dist-info/licenses/LICENSE
stytch_management-1.1.0.dist-info/METADATA
stytch_management-1.1.0.dist-info/WHEEL
stytch_management-1.1.0.dist-info/top_level.txt
stytch_management-1.1.0.dist-info/RECORD
